{
  "MeshCube|2022-07-12T14:18:18.949Z|08921": {
    "ƒ.MeshCube": {
      "idResource": "MeshCube|2022-07-12T14:18:18.949Z|08921",
      "name": "MeshCube",
      "type": "MeshCube"
    }
  },
  "Material|2022-07-12T14:18:24.933Z|27348": {
    "ƒ.Material": {
      "name": "ShaderLit",
      "idResource": "Material|2022-07-12T14:18:24.933Z|27348",
      "shader": "ShaderLit",
      "coat": {
        "ƒ.CoatColored": {
          "color": "[1, 1, 1, 1]"
        }
      }
    }
  },
  "Material|2023-06-18T17:30:27.617Z|81762": {
    "ƒ.Material": {
      "name": "ShaderLitTextured",
      "idResource": "Material|2023-06-18T17:30:27.617Z|81762",
      "shader": "ShaderLitTextured",
      "coat": {
        "ƒ.CoatTextured": {
          "color": "[1, 1, 1, 1]",
          "idTexture": "TextureImage|2023-06-18T17:29:55.436Z|59585"
        }
      }
    }
  },
  "TextureImage|2023-06-18T17:29:55.436Z|59585": {
    "ƒ.TextureImage": {
      "url": "Textures\\landscape_background.jpg",
      "type": "TextureImage",
      "Texture": {
        "idResource": "TextureImage|2023-06-18T17:29:55.436Z|59585",
        "name": "Landscape",
        "mipmap": "CRISP"
      }
    }
  },
  "Audio|2023-06-19T19:27:04.668Z|27120": {
    "ƒ.Audio": {
      "url": "Sound\\engine.mp3",
      "idResource": "Audio|2023-06-19T19:27:04.668Z|27120",
      "name": "Engine",
      "type": "Audio"
    }
  },
  "Audio|2023-06-19T19:27:57.388Z|66927": {
    "ƒ.Audio": {
      "url": "Sound\\crash.mp3",
      "idResource": "Audio|2023-06-19T19:27:57.388Z|66927",
      "name": "Crash",
      "type": "Audio"
    }
  },
  "Audio|2023-06-19T19:28:01.218Z|38551": {
    "ƒ.Audio": {
      "url": "Sound\\truck_horn.mp3",
      "idResource": "Audio|2023-06-19T19:28:01.218Z|38551",
      "name": "TruckHorn",
      "type": "Audio"
    }
  },
  "Audio|2023-06-19T19:28:09.694Z|28118": {
    "ƒ.Audio": {
      "url": "Sound\\car-pass-by.mp3",
      "idResource": "Audio|2023-06-19T19:28:09.694Z|28118",
      "name": "CarPassing",
      "type": "Audio"
    }
  },
  "Graph|2022-07-12T09:10:18.836Z|32621": {
    "ƒ.Graph": {
      "name": "Game",
      "active": true,
      "components": {},
      "children": [
        {
          "ƒ.Node": {
            "name": "Obstacles",
            "active": true,
            "components": {
              "ComponentTransform": [
                {
                  "ƒ.ComponentTransform": {
                    "local": {
                      "translation": "[0, 0, 0]",
                      "rotation": "[0, 0, 0]",
                      "scaling": "[1, 1, 1]"
                    },
                    "Component": {
                      "active": true
                    }
                  }
                }
              ]
            },
            "children": []
          }
        },
        {
          "ƒ.Node": {
            "name": "Sound",
            "active": true,
            "components": {
              "ComponentAudioListener": [
                {
                  "ƒ.ComponentAudioListener": {
                    "active": true
                  }
                }
              ],
              "ComponentAudio": [
                {
                  "ƒ.ComponentAudio": {
                    "active": true,
                    "idResource": "Audio|2023-06-19T19:27:57.388Z|66927",
                    "playing": false,
                    "loop": false,
                    "volume": 1
                  }
                },
                {
                  "ƒ.ComponentAudio": {
                    "active": true,
                    "idResource": "Audio|2023-06-19T19:28:01.218Z|38551",
                    "playing": false,
                    "loop": false,
                    "volume": 1
                  }
                },
                {
                  "ƒ.ComponentAudio": {
                    "active": true,
                    "idResource": "Audio|2023-06-19T19:28:09.694Z|28118",
                    "playing": false,
                    "loop": false,
                    "volume": 1
                  }
                },
                {
                  "ƒ.ComponentAudio": {
                    "active": true,
                    "idResource": "Audio|2023-06-19T19:27:04.668Z|27120",
                    "playing": true,
                    "loop": true,
                    "volume": 1
                  }
                }
              ]
            },
            "children": []
          }
        },
        {
          "ƒ.Node": {
            "name": "Car",
            "active": true,
            "components": {
              "ComponentMesh": [
                {
                  "ƒ.ComponentMesh": {
                    "idMesh": "MeshCube|2022-07-12T14:18:18.949Z|08921",
                    "pivot": {
                      "translation": "[0, 0, 0]",
                      "rotation": "[0, 0, 0]",
                      "scaling": "[0.30000001192092896, 1, 0.5499999523162842]"
                    },
                    "Component": {
                      "active": true
                    }
                  }
                }
              ],
              "ComponentMaterial": [
                {
                  "ƒ.ComponentMaterial": {
                    "sortForAlpha": false,
                    "clrPrimary": "[0.12156862745098039, 0.058823529411764705, 1, 1]",
                    "clrSecondary": "[1, 1, 1, 1]",
                    "pivot": {
                      "translation": "[0, 0]",
                      "rotation": 0,
                      "scaling": "[1, 1]"
                    },
                    "Component": {
                      "active": true
                    },
                    "idMaterial": "Material|2022-07-12T14:18:24.933Z|27348"
                  }
                }
              ],
              "ComponentTransform": [
                {
                  "ƒ.ComponentTransform": {
                    "local": {
                      "translation": "[0, 0.75, 0.4399999976158142]",
                      "rotation": "[0, 0, 0]",
                      "scaling": "[0.9999998807907104, 0.9999998807907104, 1]"
                    },
                    "Component": {
                      "active": true
                    }
                  }
                }
              ]
            },
            "children": []
          }
        },
        {
          "ƒ.Node": {
            "name": "Background",
            "active": true,
            "components": {
              "ComponentMesh": [
                {
                  "ƒ.ComponentMesh": {
                    "idMesh": "MeshCube|2022-07-12T14:18:18.949Z|08921",
                    "pivot": {
                      "translation": "[0, 3.5, 0]",
                      "rotation": "[0, 0, 0]",
                      "scaling": "[4, 6.37100076675415, 0.10000000149011612]"
                    },
                    "Component": {
                      "active": true
                    }
                  }
                }
              ],
              "ComponentMaterial": [
                {
                  "ƒ.ComponentMaterial": {
                    "sortForAlpha": false,
                    "clrPrimary": "[1, 1, 1, 1]",
                    "clrSecondary": "[1, 1, 1, 1]",
                    "pivot": {
                      "translation": "[0, 0]",
                      "rotation": 0,
                      "scaling": "[1, 1]"
                    },
                    "Component": {
                      "active": true
                    },
                    "idMaterial": "Material|2022-07-12T14:18:24.933Z|27348"
                  }
                }
              ]
            },
            "children": []
          }
        },
        {
          "ƒ.Node": {
            "name": "Landscape",
            "active": true,
            "components": {
              "ComponentMesh": [
                {
                  "ƒ.ComponentMesh": {
                    "idMesh": "MeshCube|2022-07-12T14:18:18.949Z|08921",
                    "pivot": {
                      "translation": "[0, 0, 0]",
                      "rotation": "[0, 0, 0]",
                      "scaling": "[20, 20, 0]"
                    },
                    "Component": {
                      "active": true
                    }
                  }
                }
              ],
              "ComponentMaterial": [
                {
                  "ƒ.ComponentMaterial": {
                    "sortForAlpha": false,
                    "clrPrimary": "[1, 1, 1, 1]",
                    "clrSecondary": "[1, 1, 1, 1]",
                    "pivot": {
                      "translation": "[0, 0]",
                      "rotation": 0,
                      "scaling": "[1, 1]"
                    },
                    "Component": {
                      "active": true
                    },
                    "idMaterial": "Material|2023-06-18T17:30:27.617Z|81762"
                  }
                }
              ],
              "ComponentTransform": [
                {
                  "ƒ.ComponentTransform": {
                    "local": {
                      "translation": "[0, 9.5, 0]",
                      "rotation": "[0, 0, 0]",
                      "scaling": "[1, 1, 1]"
                    },
                    "Component": {
                      "active": true
                    }
                  }
                }
              ]
            },
            "children": []
          }
        }
      ],
      "idResource": "Graph|2022-07-12T09:10:18.836Z|32621",
      "type": "Graph"
    }
  },
  "TextureImage|2023-06-19T19:35:34.240Z|11609": {
    "ƒ.TextureImage": {
      "url": "Textures\\Sign.png",
      "type": "TextureImage",
      "Texture": {
        "idResource": "TextureImage|2023-06-19T19:35:34.240Z|11609",
        "name": "Sign",
        "mipmap": "CRISP"
      }
    }
  }
}